storedoc/__init__.py
storedoc/local.py
storedoc/s3.py
storedoc/services.py
storedoc/spaces.py
storedoc-0.1.4.data/scripts/local.py
storedoc-0.1.4.data/scripts/s3.py
storedoc-0.1.4.data/scripts/services.py
storedoc-0.1.4.data/scripts/spaces.py
storedoc-0.1.4.dist-info/LICENSE
storedoc-0.1.4.dist-info/METADATA
storedoc-0.1.4.dist-info/WHEEL
storedoc-0.1.4.dist-info/top_level.txt
storedoc-0.1.4.dist-info/RECORD
