Metadata-Version: 2.1
Name: storedoc
Version: 0.1.4
Summary: A python library to upload files on cloud. Supported services - AWS S3, DigitalOcean Spaces, LocalStorage.
Home-page: UNKNOWN
Author: Rakesh Gunduka
Author-email: rakesh.gunduka@gmail.com
License: http://www.opensource.org/licenses/mit-license.php
Keywords: boto3 aws s3 digitalocean spaces
Platform: UNKNOWN
Classifier: Programming Language :: Python :: 3
Classifier: Programming Language :: Python :: 3.3
Classifier: Programming Language :: Python :: 3.4
Classifier: Programming Language :: Python :: 3.5
Classifier: Programming Language :: Python :: 3.6
Classifier: Development Status :: 5 - Production/Stable
Classifier: Intended Audience :: Developers
Classifier: License :: OSI Approved :: Apache Software License
Classifier: Operating System :: OS Independent
Requires-Dist: boto3
